{
  "a": "ambient.cave",
  "b": "block.anvil.break",
  "c": "block.anvil.destroy",
  "d": "block.anvil.fall",
  "e": "block.anvil.hit",
  "f": "block.anvil.land",
  "g": "block.anvil.place",
  "h": "block.anvil.step",
  "i": "block.anvil.use",
  "L": "block.brewing_stand.brew",
  "W": "block.chest.close",
  "X": "block.chest.locked",
  "Y": "block.chest.open",
  "ae": "block.chorus_flower.death",
  "af": "block.chorus_flower.grow",
  "ah": "block.cloth.break",
  "ai": "block.cloth.fall",
  "aj": "block.cloth.hit",
  "ak": "block.cloth.place",
  "al": "block.cloth.step",
  "am": "block.comparator.click",
  "av": "block.dispenser.dispense",
  "aw": "block.dispenser.fail",
  "ax": "block.dispenser.launch",
  "aM": "block.enchantment_table.use",
  "bi": "block.end_gateway.spawn",
  "aN": "block.enderchest.close",
  "aO": "block.enderchest.open",
  "bt": "block.fence_gate.close",
  "bu": "block.fence_gate.open",
  "bE": "block.fire.ambient",
  "bF": "block.fire.extinguish",
  "bH": "block.furnace.fire_crackle",
  "bZ": "block.glass.break",
  "ca": "block.glass.fall",
  "cb": "block.glass.hit",
  "cc": "block.glass.place",
  "cd": "block.glass.step",
  "ce": "block.grass.break",
  "cf": "block.grass.fall",
  "cg": "block.grass.hit",
  "ch": "block.grass.place",
  "ci": "block.grass.step",
  "cj": "block.gravel.break",
  "ck": "block.gravel.fall",
  "cl": "block.gravel.hit",
  "cm": "block.gravel.place",
  "cn": "block.gravel.step",
  "cY": "block.iron_door.close",
  "cZ": "block.iron_door.open",
  "da": "block.iron_trapdoor.close",
  "db": "block.iron_trapdoor.open",
  "dj": "block.ladder.break",
  "dk": "block.ladder.fall",
  "dl": "block.ladder.hit",
  "dm": "block.ladder.place",
  "dn": "block.ladder.step",
  "do": "block.lava.ambient",
  "dp": "block.lava.extinguish",
  "dq": "block.lava.pop",
  "dt": "block.lever.click",
  "dJ": "block.metal.break",
  "dK": "block.metal.fall",
  "dL": "block.metal.hit",
  "dM": "block.metal.place",
  "dP": "block.metal.step",
  "dN": "block.metal_pressureplate.click_off",
  "dO": "block.metal_pressureplate.click_on",
  "ed": "block.note.basedrum",
  "ee": "block.note.bass",
  "ef": "block.note.harp",
  "eg": "block.note.hat",
  "eh": "block.note.pling",
  "ei": "block.note.snare",
  "eq": "block.piston.contract",
  "er": "block.piston.extend",
  "eN": "block.portal.ambient",
  "eO": "block.portal.travel",
  "eP": "block.portal.trigger",
  "fh": "block.redstone_torch.burnout",
  "fi": "block.sand.break",
  "fj": "block.sand.fall",
  "fk": "block.sand.hit",
  "fl": "block.sand.place",
  "fm": "block.sand.step",
  "fw": "block.shulker_box.close",
  "fx": "block.shulker_box.open",
  "fU": "block.slime.break",
  "fW": "block.slime.fall",
  "fX": "block.slime.hit",
  "ga": "block.slime.place",
  "gc": "block.slime.step",
  "gp": "block.snow.break",
  "gq": "block.snow.fall",
  "gr": "block.snow.hit",
  "gs": "block.snow.place",
  "gt": "block.snow.step",
  "gD": "block.stone.break",
  "gG": "block.stone.fall",
  "gH": "block.stone.hit",
  "gI": "block.stone.place",
  "gL": "block.stone.step",
  "gE": "block.stone_button.click_off",
  "gF": "block.stone_button.click_on",
  "gJ": "block.stone_pressureplate.click_off",
  "gK": "block.stone_pressureplate.click_on",
  "gT": "block.tripwire.attach",
  "gU": "block.tripwire.click_off",
  "gV": "block.tripwire.click_on",
  "gW": "block.tripwire.detach",
  "hm": "block.water.ambient",
  "hl": "block.waterlily.place",
  "hR": "block.wood.break",
  "hU": "block.wood.fall",
  "hV": "block.wood.hit",
  "hW": "block.wood.place",
  "hZ": "block.wood.step",
  "hS": "block.wood_button.click_off",
  "hT": "block.wood_button.click_on",
  "hX": "block.wood_pressureplate.click_off",
  "hY": "block.wood_pressureplate.click_on",
  "hN": "block.wooden_door.close",
  "hO": "block.wooden_door.open",
  "hP": "block.wooden_trapdoor.close",
  "hQ": "block.wooden_trapdoor.open",
  "gQ": "enchant.thorns.hit",
  "j": "entity.armorstand.break",
  "k": "entity.armorstand.fall",
  "l": "entity.armorstand.hit",
  "m": "entity.armorstand.place",
  "t": "entity.arrow.hit",
  "u": "entity.arrow.hit_player",
  "v": "entity.arrow.shoot",
  "w": "entity.bat.ambient",
  "x": "entity.bat.death",
  "y": "entity.bat.hurt",
  "z": "entity.bat.loop",
  "A": "entity.bat.takeoff",
  "B": "entity.blaze.ambient",
  "C": "entity.blaze.burn",
  "D": "entity.blaze.death",
  "E": "entity.blaze.hurt",
  "F": "entity.blaze.shoot",
  "G": "entity.bobber.splash",
  "H": "entity.bobber.throw",
  "Q": "entity.cat.ambient",
  "R": "entity.cat.death",
  "S": "entity.cat.hiss",
  "T": "entity.cat.hurt",
  "U": "entity.cat.purr",
  "V": "entity.cat.purreow",
  "Z": "entity.chicken.ambient",
  "aa": "entity.chicken.death",
  "ab": "entity.chicken.egg",
  "ac": "entity.chicken.hurt",
  "ad": "entity.chicken.step",
  "an": "entity.cow.ambient",
  "ao": "entity.cow.death",
  "ap": "entity.cow.hurt",
  "aq": "entity.cow.milk",
  "ar": "entity.cow.step",
  "as": "entity.creeper.death",
  "at": "entity.creeper.hurt",
  "au": "entity.creeper.primed",
  "ay": "entity.donkey.ambient",
  "az": "entity.donkey.angry",
  "aA": "entity.donkey.chest",
  "aB": "entity.donkey.death",
  "aC": "entity.donkey.hurt",
  "aD": "entity.egg.throw",
  "aE": "entity.elder_guardian.ambient",
  "aF": "entity.elder_guardian.ambient_land",
  "aG": "entity.elder_guardian.curse",
  "aH": "entity.elder_guardian.death",
  "aI": "entity.elder_guardian.death_land",
  "aJ": "entity.elder_guardian.hurt",
  "aK": "entity.elder_guardian.hurt_land",
  "aP": "entity.enderdragon.ambient",
  "aQ": "entity.enderdragon.death",
  "aS": "entity.enderdragon.flap",
  "aT": "entity.enderdragon.growl",
  "aU": "entity.enderdragon.hurt",
  "aV": "entity.enderdragon.shoot",
  "aR": "entity.enderdragon_fireball.explode",
  "aW": "entity.endereye.launch",
  "aX": "entity.endermen.ambient",
  "aY": "entity.endermen.death",
  "aZ": "entity.endermen.hurt",
  "ba": "entity.endermen.scream",
  "bb": "entity.endermen.stare",
  "bc": "entity.endermen.teleport",
  "bd": "entity.endermite.ambient",
  "be": "entity.endermite.death",
  "bf": "entity.endermite.hurt",
  "bg": "entity.endermite.step",
  "bh": "entity.enderpearl.throw",
  "bj": "entity.evocation_fangs.attack",
  "bk": "entity.evocation_illager.ambient",
  "bl": "entity.evocation_illager.cast_spell",
  "bm": "entity.evocation_illager.death",
  "bn": "entity.evocation_illager.hurt",
  "bo": "entity.evocation_illager.prepare_attack",
  "bp": "entity.evocation_illager.prepare_summon",
  "bq": "entity.evocation_illager.prepare_wololo",
  "br": "entity.experience_bottle.throw",
  "bs": "entity.experience_orb.pickup",
  "bw": "entity.firework.blast",
  "bx": "entity.firework.blast_far",
  "by": "entity.firework.large_blast",
  "bz": "entity.firework.large_blast_far",
  "bA": "entity.firework.launch",
  "bB": "entity.firework.shoot",
  "bC": "entity.firework.twinkle",
  "bD": "entity.firework.twinkle_far",
  "bI": "entity.generic.big_fall",
  "bJ": "entity.generic.burn",
  "bK": "entity.generic.death",
  "bL": "entity.generic.drink",
  "bM": "entity.generic.eat",
  "bN": "entity.generic.explode",
  "bO": "entity.generic.extinguish_fire",
  "bP": "entity.generic.hurt",
  "bQ": "entity.generic.small_fall",
  "bR": "entity.generic.splash",
  "bS": "entity.generic.swim",
  "bT": "entity.ghast.ambient",
  "bU": "entity.ghast.death",
  "bV": "entity.ghast.hurt",
  "bW": "entity.ghast.scream",
  "bX": "entity.ghast.shoot",
  "bY": "entity.ghast.warn",
  "co": "entity.guardian.ambient",
  "cp": "entity.guardian.ambient_land",
  "cq": "entity.guardian.attack",
  "cr": "entity.guardian.death",
  "cs": "entity.guardian.death_land",
  "ct": "entity.guardian.flop",
  "cu": "entity.guardian.hurt",
  "cv": "entity.guardian.hurt_land",
  "cx": "entity.horse.ambient",
  "cy": "entity.horse.angry",
  "cz": "entity.horse.armor",
  "cA": "entity.horse.breathe",
  "cB": "entity.horse.death",
  "cC": "entity.horse.eat",
  "cD": "entity.horse.gallop",
  "cE": "entity.horse.hurt",
  "cF": "entity.horse.jump",
  "cG": "entity.horse.land",
  "cH": "entity.horse.saddle",
  "cI": "entity.horse.step",
  "cJ": "entity.horse.step_wood",
  "cK": "entity.hostile.big_fall",
  "cL": "entity.hostile.death",
  "cM": "entity.hostile.hurt",
  "cN": "entity.hostile.small_fall",
  "cO": "entity.hostile.splash",
  "cP": "entity.hostile.swim",
  "cQ": "entity.husk.ambient",
  "cR": "entity.husk.death",
  "cS": "entity.husk.hurt",
  "cT": "entity.husk.step",
  "cU": "entity.irongolem.attack",
  "cV": "entity.irongolem.death",
  "cW": "entity.irongolem.hurt",
  "cX": "entity.irongolem.step",
  "dh": "entity.item.break",
  "di": "entity.item.pickup",
  "dc": "entity.itemframe.add_item",
  "dd": "entity.itemframe.break",
  "de": "entity.itemframe.place",
  "df": "entity.itemframe.remove_item",
  "dg": "entity.itemframe.rotate_item",
  "dr": "entity.leashknot.break",
  "ds": "entity.leashknot.place",
  "du": "entity.lightning.impact",
  "dv": "entity.lightning.thunder",
  "dw": "entity.lingeringpotion.throw",
  "dx": "entity.llama.ambient",
  "dy": "entity.llama.angry",
  "dz": "entity.llama.death",
  "dA": "entity.llama.eat",
  "dB": "entity.llama.hurt",
  "dC": "entity.llama.spit",
  "dD": "entity.llama.step",
  "dE": "entity.llama.swag",
  "dF": "entity.magmacube.death",
  "dG": "entity.magmacube.hurt",
  "dH": "entity.magmacube.jump",
  "dI": "entity.magmacube.squish",
  "dQ": "entity.minecart.inside",
  "dR": "entity.minecart.riding",
  "dS": "entity.mooshroom.shear",
  "dT": "entity.mule.ambient",
  "dU": "entity.mule.death",
  "dV": "entity.mule.hurt",
  "ej": "entity.painting.break",
  "ek": "entity.painting.place",
  "el": "entity.pig.ambient",
  "em": "entity.pig.death",
  "en": "entity.pig.hurt",
  "eo": "entity.pig.saddle",
  "ep": "entity.pig.step",
  "es": "entity.player.attack.crit",
  "et": "entity.player.attack.knockback",
  "eu": "entity.player.attack.nodamage",
  "ev": "entity.player.attack.strong",
  "ew": "entity.player.attack.sweep",
  "ex": "entity.player.attack.weak",
  "ey": "entity.player.big_fall",
  "ez": "entity.player.breath",
  "eA": "entity.player.burp",
  "eB": "entity.player.death",
  "eC": "entity.player.hurt",
  "eD": "entity.player.levelup",
  "eE": "entity.player.small_fall",
  "eF": "entity.player.splash",
  "eG": "entity.player.swim",
  "eH": "entity.polar_bear.ambient",
  "eI": "entity.polar_bear.baby_ambient",
  "eJ": "entity.polar_bear.death",
  "eK": "entity.polar_bear.hurt",
  "eL": "entity.polar_bear.step",
  "eM": "entity.polar_bear.warning",
  "eQ": "entity.rabbit.ambient",
  "eR": "entity.rabbit.attack",
  "eS": "entity.rabbit.death",
  "eT": "entity.rabbit.hurt",
  "eU": "entity.rabbit.jump",
  "fn": "entity.sheep.ambient",
  "fo": "entity.sheep.death",
  "fp": "entity.sheep.hurt",
  "fq": "entity.sheep.shear",
  "fr": "entity.sheep.step",
  "fv": "entity.shulker.ambient",
  "fA": "entity.shulker.close",
  "fB": "entity.shulker.death",
  "fC": "entity.shulker.hurt",
  "fD": "entity.shulker.hurt_closed",
  "fE": "entity.shulker.open",
  "fF": "entity.shulker.shoot",
  "fG": "entity.shulker.teleport",
  "fy": "entity.shulker_bullet.hit",
  "fz": "entity.shulker_bullet.hurt",
  "fH": "entity.silverfish.ambient",
  "fI": "entity.silverfish.death",
  "fJ": "entity.silverfish.hurt",
  "fK": "entity.silverfish.step",
  "fL": "entity.skeleton.ambient",
  "fM": "entity.skeleton.death",
  "fQ": "entity.skeleton.hurt",
  "fR": "entity.skeleton.shoot",
  "fS": "entity.skeleton.step",
  "fN": "entity.skeleton_horse.ambient",
  "fO": "entity.skeleton_horse.death",
  "fP": "entity.skeleton_horse.hurt",
  "fT": "entity.slime.attack",
  "fV": "entity.slime.death",
  "fY": "entity.slime.hurt",
  "fZ": "entity.slime.jump",
  "gb": "entity.slime.squish",
  "gd": "entity.small_magmacube.death",
  "ge": "entity.small_magmacube.hurt",
  "gf": "entity.small_magmacube.squish",
  "gg": "entity.small_slime.death",
  "gh": "entity.small_slime.hurt",
  "gi": "entity.small_slime.jump",
  "gj": "entity.small_slime.squish",
  "gk": "entity.snowball.throw",
  "gl": "entity.snowman.ambient",
  "gm": "entity.snowman.death",
  "gn": "entity.snowman.hurt",
  "go": "entity.snowman.shoot",
  "gu": "entity.spider.ambient",
  "gv": "entity.spider.death",
  "gw": "entity.spider.hurt",
  "gx": "entity.spider.step",
  "gy": "entity.splash_potion.break",
  "gz": "entity.splash_potion.throw",
  "gA": "entity.squid.ambient",
  "gB": "entity.squid.death",
  "gC": "entity.squid.hurt",
  "gM": "entity.stray.ambient",
  "gN": "entity.stray.death",
  "gO": "entity.stray.hurt",
  "gP": "entity.stray.step",
  "gR": "entity.tnt.primed",
  "gY": "entity.vex.ambient",
  "gZ": "entity.vex.charge",
  "ha": "entity.vex.death",
  "hb": "entity.vex.hurt",
  "hc": "entity.villager.ambient",
  "hd": "entity.villager.death",
  "he": "entity.villager.hurt",
  "hf": "entity.villager.no",
  "hg": "entity.villager.trading",
  "hh": "entity.villager.yes",
  "hi": "entity.vindication_illager.ambient",
  "hj": "entity.vindication_illager.death",
  "hk": "entity.vindication_illager.hurt",
  "hp": "entity.witch.ambient",
  "hq": "entity.witch.death",
  "hr": "entity.witch.drink",
  "hs": "entity.witch.hurt",
  "ht": "entity.witch.throw",
  "hu": "entity.wither.ambient",
  "hv": "entity.wither.break_block",
  "hw": "entity.wither.death",
  "hx": "entity.wither.hurt",
  "hy": "entity.wither.shoot",
  "hD": "entity.wither.spawn",
  "hz": "entity.wither_skeleton.ambient",
  "hA": "entity.wither_skeleton.death",
  "hB": "entity.wither_skeleton.hurt",
  "hC": "entity.wither_skeleton.step",
  "hE": "entity.wolf.ambient",
  "hF": "entity.wolf.death",
  "hG": "entity.wolf.growl",
  "hH": "entity.wolf.howl",
  "hI": "entity.wolf.hurt",
  "hJ": "entity.wolf.pant",
  "hK": "entity.wolf.shake",
  "hL": "entity.wolf.step",
  "hM": "entity.wolf.whine",
  "ia": "entity.zombie.ambient",
  "ib": "entity.zombie.attack_door_wood",
  "ic": "entity.zombie.attack_iron_door",
  "id": "entity.zombie.break_door_wood",
  "ie": "entity.zombie.death",
  "ii": "entity.zombie.hurt",
  "ij": "entity.zombie.infect",
  "io": "entity.zombie.step",
  "if": "entity.zombie_horse.ambient",
  "ig": "entity.zombie_horse.death",
  "ih": "entity.zombie_horse.hurt",
  "ik": "entity.zombie_pig.ambient",
  "il": "entity.zombie_pig.angry",
  "im": "entity.zombie_pig.death",
  "in": "entity.zombie_pig.hurt",
  "ip": "entity.zombie_villager.ambient",
  "iq": "entity.zombie_villager.converted",
  "ir": "entity.zombie_villager.cure",
  "is": "entity.zombie_villager.death",
  "it": "entity.zombie_villager.hurt",
  "iu": "entity.zombie_villager.step",
  "n": "item.armor.equip_chain",
  "o": "item.armor.equip_diamond",
  "p": "item.armor.equip_generic",
  "q": "item.armor.equip_gold",
  "r": "item.armor.equip_iron",
  "s": "item.armor.equip_leather",
  "I": "item.bottle.empty",
  "J": "item.bottle.fill",
  "K": "item.bottle.fill_dragonbreath",
  "M": "item.bucket.empty",
  "N": "item.bucket.empty_lava",
  "O": "item.bucket.fill",
  "P": "item.bucket.fill_lava",
  "ag": "item.chorus_fruit.teleport",
  "aL": "item.elytra.flying",
  "bv": "item.firecharge.use",
  "bG": "item.flintandsteel.use",
  "cw": "item.hoe.till",
  "fs": "item.shield.block",
  "ft": "item.shield.break",
  "fu": "item.shovel.flatten",
  "gS": "item.totem.use",
  "dW": "music.creative",
  "dX": "music.credits",
  "dY": "music.dragon",
  "dZ": "music.end",
  "ea": "music.game",
  "eb": "music.menu",
  "ec": "music.nether",
  "eV": "record.11",
  "eW": "record.13",
  "eX": "record.blocks",
  "eY": "record.cat",
  "eZ": "record.chirp",
  "fa": "record.far",
  "fb": "record.mall",
  "fc": "record.mellohi",
  "fd": "record.stal",
  "fe": "record.strad",
  "ff": "record.wait",
  "fg": "record.ward",
  "gX": "ui.button.click",
  "hn": "weather.rain",
  "ho": "weather.rain.above"
}